{"nodes": [{"id": "svgoyml_svgo_config", "label": "SVGO Config (removeAttrs fill, fill-rule)", "file_type": "code", "source_file": "src/icons/svgo.yml", "source_location": null, "source_url": null, "captured_at": null, "author": null, "contributor": null}], "edges": [{"source": "svgoyml_svgo_config", "target": "xfork_tree_doc", "relation": "conceptually_related_to", "confidence": "INFERRED", "confidence_score": 0.65, "source_file": "src/icons/svgo.yml", "source_location": null, "weight": 1.0}], "hyperedges": []}