{"nodes": [{"id": "src_api_admin_sys_user_js", "label": "sys-user.js", "file_type": "code", "source_file": "src/api/admin/sys-user.js", "source_location": "L1"}, {"id": "sys_user_listuser", "label": "listUser()", "file_type": "code", "source_file": "src/api/admin/sys-user.js", "source_location": "L4"}, {"id": "sys_user_getuser", "label": "getUser()", "file_type": "code", "source_file": "src/api/admin/sys-user.js", "source_location": "L13"}, {"id": "sys_user_getuserinit", "label": "getUserInit()", "file_type": "code", "source_file": "src/api/admin/sys-user.js", "source_location": "L20"}, {"id": "sys_user_adduser", "label": "addUser()", "file_type": "code", "source_file": "src/api/admin/sys-user.js", "source_location": "L28"}, {"id": "sys_user_updateuser", "label": "updateUser()", "file_type": "code", "source_file": "src/api/admin/sys-user.js", "source_location": "L37"}, {"id": "sys_user_deluser", "label": "delUser()", "file_type": "code", "source_file": "src/api/admin/sys-user.js", "source_location": "L46"}, {"id": "sys_user_exportuser", "label": "exportUser()", "file_type": "code", "source_file": "src/api/admin/sys-user.js", "source_location": "L55"}, {"id": "sys_user_resetuserpwd", "label": "resetUserPwd()", "file_type": "code", "source_file": "src/api/admin/sys-user.js", "source_location": "L64"}, {"id": "sys_user_changeuserstatus", "label": "changeUserStatus()", "file_type": "code", "source_file": "src/api/admin/sys-user.js", "source_location": "L77"}, {"id": "sys_user_updateuserprofile", "label": "updateUserProfile()", "file_type": "code", "source_file": "src/api/admin/sys-user.js", "source_location": "L90"}, {"id": "sys_user_importtemplate", "label": "importTemplate()", "file_type": "code", "source_file": "src/api/admin/sys-user.js", "source_location": "L99"}, {"id": "sys_user_updateuserpwd", "label": "updateUserPwd()", "file_type": "code", "source_file": "src/api/admin/sys-user.js", "source_location": "L107"}, {"id": "sys_user_uploadavatar", "label": "uploadAvatar()", "file_type": "code", "source_file": "src/api/admin/sys-user.js", "source_location": "L120"}, {"id": "sys_user_getuserprofile", "label": "getUserProfile()", "file_type": "code", "source_file": "src/api/admin/sys-user.js", "source_location": "L129"}], "edges": [{"source": "src_api_admin_sys_user_js", "target": "request", "relation": "imports_from", "confidence": "EXTRACTED", "source_file": "src/api/admin/sys-user.js", "source_location": "L1", "weight": 1.0}, {"source": "src_api_admin_sys_user_js", "target": "sys_user_listuser", "relation": "contains", "confidence": "EXTRACTED", "source_file": "src/api/admin/sys-user.js", "source_location": "L4", "weight": 1.0}, {"source": "src_api_admin_sys_user_js", "target": "sys_user_getuser", "relation": "contains", "confidence": "EXTRACTED", "source_file": "src/api/admin/sys-user.js", "source_location": "L13", "weight": 1.0}, {"source": "src_api_admin_sys_user_js", "target": "sys_user_getuserinit", "relation": "contains", "confidence": "EXTRACTED", "source_file": "src/api/admin/sys-user.js", "source_location": "L20", "weight": 1.0}, {"source": "src_api_admin_sys_user_js", "target": "sys_user_adduser", "relation": "contains", "confidence": "EXTRACTED", "source_file": "src/api/admin/sys-user.js", "source_location": "L28", "weight": 1.0}, {"source": "src_api_admin_sys_user_js", "target": "sys_user_updateuser", "relation": "contains", "confidence": "EXTRACTED", "source_file": "src/api/admin/sys-user.js", "source_location": "L37", "weight": 1.0}, {"source": "src_api_admin_sys_user_js", "target": "sys_user_deluser", "relation": "contains", "confidence": "EXTRACTED", "source_file": "src/api/admin/sys-user.js", "source_location": "L46", "weight": 1.0}, {"source": "src_api_admin_sys_user_js", "target": "sys_user_exportuser", "relation": "contains", "confidence": "EXTRACTED", "source_file": "src/api/admin/sys-user.js", "source_location": "L55", "weight": 1.0}, {"source": "src_api_admin_sys_user_js", "target": "sys_user_resetuserpwd", "relation": "contains", "confidence": "EXTRACTED", "source_file": "src/api/admin/sys-user.js", "source_location": "L64", "weight": 1.0}, {"source": "src_api_admin_sys_user_js", "target": "sys_user_changeuserstatus", "relation": "contains", "confidence": "EXTRACTED", "source_file": "src/api/admin/sys-user.js", "source_location": "L77", "weight": 1.0}, {"source": "src_api_admin_sys_user_js", "target": "sys_user_updateuserprofile", "relation": "contains", "confidence": "EXTRACTED", "source_file": "src/api/admin/sys-user.js", "source_location": "L90", "weight": 1.0}, {"source": "src_api_admin_sys_user_js", "target": "sys_user_importtemplate", "relation": "contains", "confidence": "EXTRACTED", "source_file": "src/api/admin/sys-user.js", "source_location": "L99", "weight": 1.0}, {"source": "src_api_admin_sys_user_js", "target": "sys_user_updateuserpwd", "relation": "contains", "confidence": "EXTRACTED", "source_file": "src/api/admin/sys-user.js", "source_location": "L107", "weight": 1.0}, {"source": "src_api_admin_sys_user_js", "target": "sys_user_uploadavatar", "relation": "contains", "confidence": "EXTRACTED", "source_file": "src/api/admin/sys-user.js", "source_location": "L120", "weight": 1.0}, {"source": "src_api_admin_sys_user_js", "target": "sys_user_getuserprofile", "relation": "contains", "confidence": "EXTRACTED", "source_file": "src/api/admin/sys-user.js", "source_location": "L129", "weight": 1.0}], "raw_calls": [{"caller_nid": "sys_user_listuser", "callee": "request", "source_file": "src/api/admin/sys-user.js", "source_location": "L5"}, {"caller_nid": "sys_user_getuser", "callee": "request", "source_file": "src/api/admin/sys-user.js", "source_location": "L14"}, {"caller_nid": "sys_user_getuserinit", "callee": "request", "source_file": "src/api/admin/sys-user.js", "source_location": "L21"}, {"caller_nid": "sys_user_adduser", "callee": "request", "source_file": "src/api/admin/sys-user.js", "source_location": "L29"}, {"caller_nid": "sys_user_updateuser", "callee": "request", "source_file": "src/api/admin/sys-user.js", "source_location": "L38"}, {"caller_nid": "sys_user_deluser", "callee": "request", "source_file": "src/api/admin/sys-user.js", "source_location": "L47"}, {"caller_nid": "sys_user_exportuser", "callee": "request", "source_file": "src/api/admin/sys-user.js", "source_location": "L56"}, {"caller_nid": "sys_user_resetuserpwd", "callee": "request", "source_file": "src/api/admin/sys-user.js", "source_location": "L69"}, {"caller_nid": "sys_user_changeuserstatus", "callee": "request", "source_file": "src/api/admin/sys-user.js", "source_location": "L82"}, {"caller_nid": "sys_user_updateuserprofile", "callee": "request", "source_file": "src/api/admin/sys-user.js", "source_location": "L91"}, {"caller_nid": "sys_user_importtemplate", "callee": "request", "source_file": "src/api/admin/sys-user.js", "source_location": "L100"}, {"caller_nid": "sys_user_updateuserpwd", "callee": "request", "source_file": "src/api/admin/sys-user.js", "source_location": "L112"}, {"caller_nid": "sys_user_uploadavatar", "callee": "request", "source_file": "src/api/admin/sys-user.js", "source_location": "L121"}, {"caller_nid": "sys_user_getuserprofile", "callee": "request", "source_file": "src/api/admin/sys-user.js", "source_location": "L130"}]}