{"nodes": [{"id": "src_api_admin_sys_post_js", "label": "sys-post.js", "file_type": "code", "source_file": "src/api/admin/sys-post.js", "source_location": "L1"}, {"id": "sys_post_listpost", "label": "listPost()", "file_type": "code", "source_file": "src/api/admin/sys-post.js", "source_location": "L4"}, {"id": "sys_post_getpost", "label": "getPost()", "file_type": "code", "source_file": "src/api/admin/sys-post.js", "source_location": "L13"}, {"id": "sys_post_addpost", "label": "addPost()", "file_type": "code", "source_file": "src/api/admin/sys-post.js", "source_location": "L21"}, {"id": "sys_post_updatepost", "label": "updatePost()", "file_type": "code", "source_file": "src/api/admin/sys-post.js", "source_location": "L30"}, {"id": "sys_post_delpost", "label": "delPost()", "file_type": "code", "source_file": "src/api/admin/sys-post.js", "source_location": "L39"}], "edges": [{"source": "src_api_admin_sys_post_js", "target": "request", "relation": "imports_from", "confidence": "EXTRACTED", "source_file": "src/api/admin/sys-post.js", "source_location": "L1", "weight": 1.0}, {"source": "src_api_admin_sys_post_js", "target": "sys_post_listpost", "relation": "contains", "confidence": "EXTRACTED", "source_file": "src/api/admin/sys-post.js", "source_location": "L4", "weight": 1.0}, {"source": "src_api_admin_sys_post_js", "target": "sys_post_getpost", "relation": "contains", "confidence": "EXTRACTED", "source_file": "src/api/admin/sys-post.js", "source_location": "L13", "weight": 1.0}, {"source": "src_api_admin_sys_post_js", "target": "sys_post_addpost", "relation": "contains", "confidence": "EXTRACTED", "source_file": "src/api/admin/sys-post.js", "source_location": "L21", "weight": 1.0}, {"source": "src_api_admin_sys_post_js", "target": "sys_post_updatepost", "relation": "contains", "confidence": "EXTRACTED", "source_file": "src/api/admin/sys-post.js", "source_location": "L30", "weight": 1.0}, {"source": "src_api_admin_sys_post_js", "target": "sys_post_delpost", "relation": "contains", "confidence": "EXTRACTED", "source_file": "src/api/admin/sys-post.js", "source_location": "L39", "weight": 1.0}], "raw_calls": [{"caller_nid": "sys_post_listpost", "callee": "request", "source_file": "src/api/admin/sys-post.js", "source_location": "L5"}, {"caller_nid": "sys_post_getpost", "callee": "request", "source_file": "src/api/admin/sys-post.js", "source_location": "L14"}, {"caller_nid": "sys_post_addpost", "callee": "request", "source_file": "src/api/admin/sys-post.js", "source_location": "L22"}, {"caller_nid": "sys_post_updatepost", "callee": "request", "source_file": "src/api/admin/sys-post.js", "source_location": "L31"}, {"caller_nid": "sys_post_delpost", "callee": "request", "source_file": "src/api/admin/sys-post.js", "source_location": "L40"}]}