{"nodes": [{"id": "src_api_admin_sys_dept_js", "label": "sys-dept.js", "file_type": "code", "source_file": "src/api/admin/sys-dept.js", "source_location": "L1"}, {"id": "sys_dept_getdeptlist", "label": "getDeptList()", "file_type": "code", "source_file": "src/api/admin/sys-dept.js", "source_location": "L3"}, {"id": "sys_dept_getdept", "label": "getDept()", "file_type": "code", "source_file": "src/api/admin/sys-dept.js", "source_location": "L12"}, {"id": "sys_dept_treeselect", "label": "treeselect()", "file_type": "code", "source_file": "src/api/admin/sys-dept.js", "source_location": "L20"}, {"id": "sys_dept_roledepttreeselect", "label": "roleDeptTreeselect()", "file_type": "code", "source_file": "src/api/admin/sys-dept.js", "source_location": "L28"}, {"id": "sys_dept_adddept", "label": "addDept()", "file_type": "code", "source_file": "src/api/admin/sys-dept.js", "source_location": "L36"}, {"id": "sys_dept_updatedept", "label": "updateDept()", "file_type": "code", "source_file": "src/api/admin/sys-dept.js", "source_location": "L45"}, {"id": "sys_dept_deldept", "label": "delDept()", "file_type": "code", "source_file": "src/api/admin/sys-dept.js", "source_location": "L54"}], "edges": [{"source": "src_api_admin_sys_dept_js", "target": "request", "relation": "imports_from", "confidence": "EXTRACTED", "source_file": "src/api/admin/sys-dept.js", "source_location": "L1", "weight": 1.0}, {"source": "src_api_admin_sys_dept_js", "target": "sys_dept_getdeptlist", "relation": "contains", "confidence": "EXTRACTED", "source_file": "src/api/admin/sys-dept.js", "source_location": "L3", "weight": 1.0}, {"source": "src_api_admin_sys_dept_js", "target": "sys_dept_getdept", "relation": "contains", "confidence": "EXTRACTED", "source_file": "src/api/admin/sys-dept.js", "source_location": "L12", "weight": 1.0}, {"source": "src_api_admin_sys_dept_js", "target": "sys_dept_treeselect", "relation": "contains", "confidence": "EXTRACTED", "source_file": "src/api/admin/sys-dept.js", "source_location": "L20", "weight": 1.0}, {"source": "src_api_admin_sys_dept_js", "target": "sys_dept_roledepttreeselect", "relation": "contains", "confidence": "EXTRACTED", "source_file": "src/api/admin/sys-dept.js", "source_location": "L28", "weight": 1.0}, {"source": "src_api_admin_sys_dept_js", "target": "sys_dept_adddept", "relation": "contains", "confidence": "EXTRACTED", "source_file": "src/api/admin/sys-dept.js", "source_location": "L36", "weight": 1.0}, {"source": "src_api_admin_sys_dept_js", "target": "sys_dept_updatedept", "relation": "contains", "confidence": "EXTRACTED", "source_file": "src/api/admin/sys-dept.js", "source_location": "L45", "weight": 1.0}, {"source": "src_api_admin_sys_dept_js", "target": "sys_dept_deldept", "relation": "contains", "confidence": "EXTRACTED", "source_file": "src/api/admin/sys-dept.js", "source_location": "L54", "weight": 1.0}], "raw_calls": [{"caller_nid": "sys_dept_getdeptlist", "callee": "request", "source_file": "src/api/admin/sys-dept.js", "source_location": "L4"}, {"caller_nid": "sys_dept_getdept", "callee": "request", "source_file": "src/api/admin/sys-dept.js", "source_location": "L13"}, {"caller_nid": "sys_dept_treeselect", "callee": "request", "source_file": "src/api/admin/sys-dept.js", "source_location": "L21"}, {"caller_nid": "sys_dept_roledepttreeselect", "callee": "request", "source_file": "src/api/admin/sys-dept.js", "source_location": "L29"}, {"caller_nid": "sys_dept_adddept", "callee": "request", "source_file": "src/api/admin/sys-dept.js", "source_location": "L37"}, {"caller_nid": "sys_dept_updatedept", "callee": "request", "source_file": "src/api/admin/sys-dept.js", "source_location": "L46"}, {"caller_nid": "sys_dept_deldept", "callee": "request", "source_file": "src/api/admin/sys-dept.js", "source_location": "L55"}]}