{"nodes": [{"id": "src_api_job_sys_job_js", "label": "sys-job.js", "file_type": "code", "source_file": "src/api/job/sys-job.js", "source_location": "L1"}, {"id": "sys_job_listsysjob", "label": "listSysJob()", "file_type": "code", "source_file": "src/api/job/sys-job.js", "source_location": "L4"}, {"id": "sys_job_getsysjob", "label": "getSysJob()", "file_type": "code", "source_file": "src/api/job/sys-job.js", "source_location": "L13"}, {"id": "sys_job_addsysjob", "label": "addSysJob()", "file_type": "code", "source_file": "src/api/job/sys-job.js", "source_location": "L21"}, {"id": "sys_job_updatesysjob", "label": "updateSysJob()", "file_type": "code", "source_file": "src/api/job/sys-job.js", "source_location": "L30"}, {"id": "sys_job_delsysjob", "label": "delSysJob()", "file_type": "code", "source_file": "src/api/job/sys-job.js", "source_location": "L39"}, {"id": "sys_job_removejob", "label": "removeJob()", "file_type": "code", "source_file": "src/api/job/sys-job.js", "source_location": "L48"}, {"id": "sys_job_startjob", "label": "startJob()", "file_type": "code", "source_file": "src/api/job/sys-job.js", "source_location": "L56"}], "edges": [{"source": "src_api_job_sys_job_js", "target": "request", "relation": "imports_from", "confidence": "EXTRACTED", "source_file": "src/api/job/sys-job.js", "source_location": "L1", "weight": 1.0}, {"source": "src_api_job_sys_job_js", "target": "sys_job_listsysjob", "relation": "contains", "confidence": "EXTRACTED", "source_file": "src/api/job/sys-job.js", "source_location": "L4", "weight": 1.0}, {"source": "src_api_job_sys_job_js", "target": "sys_job_getsysjob", "relation": "contains", "confidence": "EXTRACTED", "source_file": "src/api/job/sys-job.js", "source_location": "L13", "weight": 1.0}, {"source": "src_api_job_sys_job_js", "target": "sys_job_addsysjob", "relation": "contains", "confidence": "EXTRACTED", "source_file": "src/api/job/sys-job.js", "source_location": "L21", "weight": 1.0}, {"source": "src_api_job_sys_job_js", "target": "sys_job_updatesysjob", "relation": "contains", "confidence": "EXTRACTED", "source_file": "src/api/job/sys-job.js", "source_location": "L30", "weight": 1.0}, {"source": "src_api_job_sys_job_js", "target": "sys_job_delsysjob", "relation": "contains", "confidence": "EXTRACTED", "source_file": "src/api/job/sys-job.js", "source_location": "L39", "weight": 1.0}, {"source": "src_api_job_sys_job_js", "target": "sys_job_removejob", "relation": "contains", "confidence": "EXTRACTED", "source_file": "src/api/job/sys-job.js", "source_location": "L48", "weight": 1.0}, {"source": "src_api_job_sys_job_js", "target": "sys_job_startjob", "relation": "contains", "confidence": "EXTRACTED", "source_file": "src/api/job/sys-job.js", "source_location": "L56", "weight": 1.0}], "raw_calls": [{"caller_nid": "sys_job_listsysjob", "callee": "request", "source_file": "src/api/job/sys-job.js", "source_location": "L5"}, {"caller_nid": "sys_job_getsysjob", "callee": "request", "source_file": "src/api/job/sys-job.js", "source_location": "L14"}, {"caller_nid": "sys_job_addsysjob", "callee": "request", "source_file": "src/api/job/sys-job.js", "source_location": "L22"}, {"caller_nid": "sys_job_updatesysjob", "callee": "request", "source_file": "src/api/job/sys-job.js", "source_location": "L31"}, {"caller_nid": "sys_job_delsysjob", "callee": "request", "source_file": "src/api/job/sys-job.js", "source_location": "L40"}, {"caller_nid": "sys_job_removejob", "callee": "request", "source_file": "src/api/job/sys-job.js", "source_location": "L49"}, {"caller_nid": "sys_job_startjob", "callee": "request", "source_file": "src/api/job/sys-job.js", "source_location": "L57"}]}